plotirr/__init__.py
plotirr/initiate.py
plotirr/irreversible.mplstyle
plotirr/util.py
plotirr/report_maker/__init__.py
plotirr/report_maker/output.py
PlotIrreversible-0.2.dist-info/LICENSE
PlotIrreversible-0.2.dist-info/METADATA
PlotIrreversible-0.2.dist-info/WHEEL
PlotIrreversible-0.2.dist-info/top_level.txt
PlotIrreversible-0.2.dist-info/RECORD
