Metadata-Version: 2.1
Name: PlotIrreversible
Version: 0.2
Summary: Set matplotlib style to conform with Irreversible's brand policies
Author: Kyle Mills
Author-email: kyle.mills@irreversible.tech
License-File: LICENSE
Requires-Dist: tabulate
Requires-Dist: matplotlib (>=3.1.0)
Requires-Dist: gif
Requires-Dist: tqdm
Requires-Dist: numpy
